safestr.py
setup.py
safestr.egg-info/PKG-INFO
safestr.egg-info/SOURCES.txt
safestr.egg-info/dependency_links.txt
safestr.egg-info/entry_points.txt
safestr.egg-info/not-zip-safe
safestr.egg-info/top_level.txt