Metadata-Version: 1.0
Name: safestr
Version: 1.1.0
Summary: Ultimate python unicode/types solution, run well with both python 2 and python3
Home-page: http://jerrychen1990.github.io
Author: jerrychen
Author-email: jerrychen1990@gmail.com
License: UNKNOWN
Keywords: safe,str,py2,py3
Platform: UNKNOWN
